.coveragerc
.travis.yml
CHANGELOG.rst
LICENSE
MANIFEST.in
Pipfile
Pipfile.lock
README.rst
requirements.txt
setup.cfg
setup.py
test-requirements.txt
tox.ini
src/AsyncOpenStackClient.egg-info/PKG-INFO
src/AsyncOpenStackClient.egg-info/SOURCES.txt
src/AsyncOpenStackClient.egg-info/dependency_links.txt
src/AsyncOpenStackClient.egg-info/not-zip-safe
src/AsyncOpenStackClient.egg-info/requires.txt
src/AsyncOpenStackClient.egg-info/top_level.txt
src/asyncopenstackclient/__init__.py
src/asyncopenstackclient/auth.py
src/asyncopenstackclient/cinder.py
src/asyncopenstackclient/client.py
src/asyncopenstackclient/glance.py
src/asyncopenstackclient/nova.py
src/asyncopenstackclient/proxy.py
tests/__init__.py
tests/test_auth.py
tests/test_client.py
tests/test_proxy.py