Metadata-Version: 1.1
Name: AsyncOpenStackClient
Version: 0.8.1
Summary: Basic OpenStack async client library using asyncio
Home-page: https://github.com/DreamLab/AsyncOpenStackClient
Author: Dreamlab - PaaS KRK
Author-email: paas-support@dreamlab.pl
License: UNKNOWN
Keywords: iaas,cloud,openstack,nova,glance,async
Platform: UNKNOWN
Classifier: Programming Language :: Python :: 3.5
Classifier: Programming Language :: Python :: 3.6
Classifier: Programming Language :: Python :: 3.7
Classifier: Operating System :: POSIX
Classifier: Development Status :: 4 - Beta
